cs/tarutils.py
cs.tarutils-20240318.dist-info/METADATA
cs.tarutils-20240318.dist-info/WHEEL
cs.tarutils-20240318.dist-info/top_level.txt
cs.tarutils-20240318.dist-info/RECORD
