Metadata-Version: 2.1
Name: cs.tarutils
Version: 20240318
Summary: Assorted tar related things, including a fast tar-based copy.
Author-email: Cameron Simpson <cs@cskk.id.au>
License: GNU General Public License v3 or later (GPLv3+)
Project-URL: URL, https://bitbucket.org/cameron_simpson/css/commits/all
Keywords: python3
Platform: UNKNOWN
Classifier: Programming Language :: Python
Classifier: Programming Language :: Python :: 3
Classifier: Development Status :: 4 - Beta
Classifier: Intended Audience :: Developers
Classifier: Operating System :: OS Independent
Classifier: Topic :: Software Development :: Libraries :: Python Modules
Classifier: License :: OSI Approved :: GNU General Public License v3 or later (GPLv3+)
Requires-Dist: cs.deco >=20240316
Requires-Dist: cs.fs >=20240316
Requires-Dist: cs.gimmicks >=20240316
Requires-Dist: cs.pfx >=20230604
Requires-Dist: cs.progress >=20230401
Requires-Dist: cs.queues >=20240318
Requires-Dist: cs.units
Requires-Dist: cs.upd >=20240316
